{
  "captured_at": "2026-03-09T14:50:46.094726+00:00",
  "run_id": "chk_d535260dcf1f",
  "scope": "quick",
  "status": "success",
  "requested_by": "test",
  "started_at": "2026-03-09T14:50:45.100257+00:00",
  "finished_at": "2026-03-09T14:50:46.094429+00:00",
  "exit_code": 0,
  "log_path": "/Users/andyxu/Documents/project/wherecode/.wherecode/check_runs/chk_d535260dcf1f.log",
  "command_text": "bash /Users/andyxu/Documents/project/wherecode/scripts/check_all_local.sh quick",
  "message": "check run passed",
  "last_output": "[1/1] backend quick checks\n.................................                                        [100%]\n33 passed in 0.39s\nchecks passed (scope=quick)"
}
